airgen/__init__.py
airgen/client.py
airgen/types.py
airgen/utils/__init__.py
airgen/utils/collect.py
airgen/utils/controller.py
airgen/utils/general.py
airgen/utils/geodetic.py
airgen/utils/mechanics.py
airgen/utils/sensor.py
airgen/utils/trajectory.py
airgen/utils/vision.py
airgen/utils/visualize.py
airgen_third_party/__init__.py
airgen_third_party/msgpackrpc/__init__.py
airgen_third_party/msgpackrpc/_version.py
airgen_third_party/msgpackrpc/address.py
airgen_third_party/msgpackrpc/client.py
airgen_third_party/msgpackrpc/compat.py
airgen_third_party/msgpackrpc/error.py
airgen_third_party/msgpackrpc/future.py
airgen_third_party/msgpackrpc/loop.py
airgen_third_party/msgpackrpc/message.py
airgen_third_party/msgpackrpc/server.py
airgen_third_party/msgpackrpc/session.py
airgen_third_party/msgpackrpc/tornado/__init__.py
airgen_third_party/msgpackrpc/tornado/_locale_data.py
airgen_third_party/msgpackrpc/tornado/auth.py
airgen_third_party/msgpackrpc/tornado/autoreload.py
airgen_third_party/msgpackrpc/tornado/concurrent.py
airgen_third_party/msgpackrpc/tornado/curl_httpclient.py
airgen_third_party/msgpackrpc/tornado/escape.py
airgen_third_party/msgpackrpc/tornado/gen.py
airgen_third_party/msgpackrpc/tornado/http1connection.py
airgen_third_party/msgpackrpc/tornado/httpclient.py
airgen_third_party/msgpackrpc/tornado/httpserver.py
airgen_third_party/msgpackrpc/tornado/httputil.py
airgen_third_party/msgpackrpc/tornado/ioloop.py
airgen_third_party/msgpackrpc/tornado/iostream.py
airgen_third_party/msgpackrpc/tornado/locale.py
airgen_third_party/msgpackrpc/tornado/locks.py
airgen_third_party/msgpackrpc/tornado/log.py
airgen_third_party/msgpackrpc/tornado/netutil.py
airgen_third_party/msgpackrpc/tornado/options.py
airgen_third_party/msgpackrpc/tornado/process.py
airgen_third_party/msgpackrpc/tornado/queues.py
airgen_third_party/msgpackrpc/tornado/routing.py
airgen_third_party/msgpackrpc/tornado/simple_httpclient.py
airgen_third_party/msgpackrpc/tornado/stack_context.py
airgen-0.0.11.dist-info/LICENSE
airgen-0.0.11.dist-info/METADATA
airgen-0.0.11.dist-info/WHEEL
airgen-0.0.11.dist-info/top_level.txt
airgen-0.0.11.dist-info/RECORD
